shipmmg/__init__.py
shipmmg/draw_obj.py
shipmmg/kt.py
shipmmg/mmg_3dof.py
shipmmg/ship_obj_3dof.py
shipmmg-0.0.10.dist-info/LICENSE
shipmmg-0.0.10.dist-info/WHEEL
shipmmg-0.0.10.dist-info/METADATA
shipmmg-0.0.10.dist-info/RECORD
