Metadata-Version: 2.1
Name: shipmmg
Version: 0.0.10
Summary: A Python package of ship maneuvering simulation
Home-page: https://github.com/ShipMMG/shipmmg
License: MIT
Author: Taiga MITSUYUKI
Author-email: mitsuyuki-taiga-my@ynu.ac.jp
Requires-Python: >=3.8,<4.0
Classifier: License :: OSI Approved :: MIT License
Classifier: Programming Language :: Python :: 3
Classifier: Programming Language :: Python :: 3.10
Classifier: Programming Language :: Python :: 3.8
Classifier: Programming Language :: Python :: 3.9
Requires-Dist: Pillow (>=9.4.0,<10.0.0)
Requires-Dist: matplotlib (>=3.6.0,<4.0.0)
Requires-Dist: numpy (>=1.24.2,<2.0.0)
Requires-Dist: pytest-cov (>=3,<4)
Requires-Dist: scipy (>=1.9.0,<2.0.0)
Project-URL: Documentation, https://shipmmg.github.io/shipmmg/
Project-URL: Repository, https://github.com/ShipMMG/shipmmg
